README.md
setup.py
reposit/__init__.py
reposit/settings.py
reposit.egg-info/PKG-INFO
reposit.egg-info/SOURCES.txt
reposit.egg-info/dependency_links.txt
reposit.egg-info/requires.txt
reposit.egg-info/top_level.txt
reposit/auth/__init__.py
reposit/auth/account.py
reposit/auth/connect.py
reposit/auth/exceptions.py
reposit/data/__init__.py
reposit/data/api.py
reposit/data/controller.py
reposit/data/exceptions.py
reposit/data/utils.py
reposit/utilities/__init__.py
reposit/utilities/utils.py
reposit_tests/__init__.py
reposit_tests/formatting_fixtures.py
reposit_tests/test_deepest_key.py
reposit_tests/test_is_valid_url.py
reposit_tests/test_match_schema.py
scripts/__init__.py
scripts/test.py