Metadata-Version: 2.1
Name: reposit
Version: 0.4.0
Summary: A library to communicate with a Reposit Controller
Home-page: https://github.com/RepositPower/reposit-python-client
Author: Thomas Basche
Author-email: thomas.basche@repositpower.com
License: UNKNOWN
Platform: UNKNOWN
Classifier: Programming Language :: Python :: 3.7
Classifier: Programming Language :: Python :: 3.6
Classifier: Programming Language :: Python :: 3.5
Classifier: Programming Language :: Python :: 3.4
Classifier: Programming Language :: Python :: 2.7
Classifier: License :: OSI Approved :: Apache Software License
Classifier: Operating System :: OS Independent
